phadd/phadd.py
parallel_hadd-1.2.dist-info/LICENSE
parallel_hadd-1.2.dist-info/METADATA
parallel_hadd-1.2.dist-info/WHEEL
parallel_hadd-1.2.dist-info/entry_points.txt
parallel_hadd-1.2.dist-info/top_level.txt
parallel_hadd-1.2.dist-info/RECORD
