Metadata-Version: 2.1
Name: parallel-hadd
Version: 1.2
Summary: A python package to hadd files in parallel
Home-page: https://github.com/MohamedElashri/hadd-parallel
Author: Mohamed Elashri
Author-email: muhammadelashri@gmail.com
License: MIT
Keywords: hadd,ROOT,ROOT histogram,Physics,ROOT CERN,Histograms
Platform: any
Classifier: Development Status :: 4 - Beta
Classifier: Environment :: Console
Classifier: Intended Audience :: Science/Research
Classifier: License :: OSI Approved :: MIT License 
Classifier: Natural Language :: English
Classifier: Operating System :: OS Independent
Classifier: Programming Language :: Python :: 3.6
Classifier: Programming Language :: Python :: 3.7
Classifier: Programming Language :: Python :: 3.8
Classifier: Topic :: Scientific/Engineering :: Physics
Requires-Python: >=3.6, <4
License-File: LICENSE
